{
  "_format": "ethers-rs-sol-cache-3",
  "paths": {
    "artifacts": "out",
    "build_infos": "out/build-info",
    "sources": "src",
    "tests": "test",
    "scripts": "script",
    "libraries": [
      "lib"
    ]
  },
  "files": {
    "lib/forge-std/lib/ds-test/src/test.sol": {
      "lastModificationDate": 1691430202801,
      "contentHash": "9febff9d09f18af5306669dc276c4c43",
      "sourceName": "lib/forge-std/lib/ds-test/src/test.sol",
      "solcConfig": {
        "settings": {
          "optimizer": {
            "enabled": true,
            "runs": 200
          },
          "metadata": {
            "useLiteralContent": false,
            "bytecodeHash": "ipfs",
            "appendCBOR": true
          },
          "outputSelection": {
            "*": {
              "": [
                "ast"
              ],
              "*": [
                "abi",
                "evm.bytecode",
                "evm.deployedBytecode",
                "evm.methodIdentifiers",
                "metadata"
              ]
            }
          },
          "evmVersion": "paris",
          "libraries": {}
        }
      },
      "imports": [],
      "versionRequirement": ">=0.5.0",
      "artifacts": {
        "DSTest": {
          "0.8.21+commit.d9974bed.Darwin.appleclang": "test.sol/DSTest.json"
        }
      }
    },
    "lib/forge-std/src/Base.sol": {
      "lastModificationDate": 1691430201971,
      "contentHash": "ee13c050b1914464f1d3f90cde90204b",
      "sourceName": "lib/forge-std/src/Base.sol",
      "solcConfig": {
        "settings": {
          "optimizer": {
            "enabled": true,
            "runs": 200
          },
          "metadata": {
            "useLiteralContent": false,
            "bytecodeHash": "ipfs",
            "appendCBOR": true
          },
          "outputSelection": {
            "*": {
              "": [
                "ast"
              ],
              "*": [
                "abi",
                "evm.bytecode",
                "evm.deployedBytecode",
                "evm.methodIdentifiers",
                "metadata"
              ]
            }
          },
          "evmVersion": "paris",
          "libraries": {}
        }
      },
      "imports": [
        "lib/forge-std/src/StdStorage.sol",
        "lib/forge-std/src/Vm.sol"
      ],
      "versionRequirement": ">=0.6.2, <0.9.0",
      "artifacts": {
        "CommonBase": {
          "0.8.21+commit.d9974bed.Darwin.appleclang": "Base.sol/CommonBase.json"
        },
        "ScriptBase": {
          "0.8.21+commit.d9974bed.Darwin.appleclang": "Base.sol/ScriptBase.json"
        },
        "TestBase": {
          "0.8.21+commit.d9974bed.Darwin.appleclang": "Base.sol/TestBase.json"
        }
      }
    },
    "lib/forge-std/src/Script.sol": {
      "lastModificationDate": 1691430202839,
      "contentHash": "a8896f13ebff9ed23cce0fcb7f8f1984",
      "sourceName": "lib/forge-std/src/Script.sol",
      "solcConfig": {
        "settings": {
          "optimizer": {
            "enabled": true,
            "runs": 200
          },
          "metadata": {
            "useLiteralContent": false,
            "bytecodeHash": "ipfs",
            "appendCBOR": true
          },
          "outputSelection": {
            "*": {
              "": [
                "ast"
              ],
              "*": [
                "abi",
                "evm.bytecode",
                "evm.deployedBytecode",
                "evm.methodIdentifiers",
                "metadata"
              ]
            }
          },
          "evmVersion": "paris",
          "libraries": {}
        }
      },
      "imports": [
        "lib/forge-std/src/Base.sol",
        "lib/forge-std/src/StdChains.sol",
        "lib/forge-std/src/StdCheats.sol",
        "lib/forge-std/src/StdJson.sol",
        "lib/forge-std/src/StdMath.sol",
        "lib/forge-std/src/StdStorage.sol",
        "lib/forge-std/src/StdStyle.sol",
        "lib/forge-std/src/StdUtils.sol",
        "lib/forge-std/src/Vm.sol",
        "lib/forge-std/src/console.sol",
        "lib/forge-std/src/console2.sol",
        "lib/forge-std/src/interfaces/IMulticall3.sol",
        "lib/forge-std/src/safeconsole.sol"
      ],
      "versionRequirement": ">=0.6.2, <0.9.0",
      "artifacts": {
        "Script": {
          "0.8.21+commit.d9974bed.Darwin.appleclang": "Script.sol/Script.json"
        }
      }
    },
    "lib/forge-std/src/StdAssertions.sol": {
      "lastModificationDate": 1691430201971,
      "contentHash": "6cc2858240bcd443debbbf075490e325",
      "sourceName": "lib/forge-std/src/StdAssertions.sol",
      "solcConfig": {
        "settings": {
          "optimizer": {
            "enabled": true,
            "runs": 200
          },
          "metadata": {
            "useLiteralContent": false,
            "bytecodeHash": "ipfs",
            "appendCBOR": true
          },
          "outputSelection": {
            "*": {
              "": [
                "ast"
              ],
              "*": [
                "abi",
                "evm.bytecode",
                "evm.deployedBytecode",
                "evm.methodIdentifiers",
                "metadata"
              ]
            }
          },
          "evmVersion": "paris",
          "libraries": {}
        }
      },
      "imports": [
        "lib/forge-std/lib/ds-test/src/test.sol",
        "lib/forge-std/src/StdMath.sol"
      ],
      "versionRequirement": ">=0.6.2, <0.9.0",
      "artifacts": {
        "StdAssertions": {
          "0.8.21+commit.d9974bed.Darwin.appleclang": "StdAssertions.sol/StdAssertions.json"
        }
      }
    },
    "lib/forge-std/src/StdChains.sol": {
      "lastModificationDate": 1691430202839,
      "contentHash": "aff0685683a41d8e314d64aef646fe6f",
      "sourceName": "lib/forge-std/src/StdChains.sol",
      "solcConfig": {
        "settings": {
          "optimizer": {
            "enabled": true,
            "runs": 200
          },
          "metadata": {
            "useLiteralContent": false,
            "bytecodeHash": "ipfs",
            "appendCBOR": true
          },
          "outputSelection": {
            "*": {
              "": [
                "ast"
              ],
              "*": [
                "abi",
                "evm.bytecode",
                "evm.deployedBytecode",
                "evm.methodIdentifiers",
                "metadata"
              ]
            }
          },
          "evmVersion": "paris",
          "libraries": {}
        }
      },
      "imports": [
        "lib/forge-std/src/Vm.sol"
      ],
      "versionRequirement": ">=0.6.2, <0.9.0",
      "artifacts": {
        "StdChains": {
          "0.8.21+commit.d9974bed.Darwin.appleclang": "StdChains.sol/StdChains.json"
        }
      }
    },
    "lib/forge-std/src/StdCheats.sol": {
      "lastModificationDate": 1691430201971,
      "contentHash": "27745bb24c5568c75c3043277ee18bcb",
      "sourceName": "lib/forge-std/src/StdCheats.sol",
      "solcConfig": {
        "settings": {
          "optimizer": {
            "enabled": true,
            "runs": 200
          },
          "metadata": {
            "useLiteralContent": false,
            "bytecodeHash": "ipfs",
            "appendCBOR": true
          },
          "outputSelection": {
            "*": {
              "": [
                "ast"
              ],
              "*": [
                "abi",
                "evm.bytecode",
                "evm.deployedBytecode",
                "evm.methodIdentifiers",
                "metadata"
              ]
            }
          },
          "evmVersion": "paris",
          "libraries": {}
        }
      },
      "imports": [
        "lib/forge-std/src/StdStorage.sol",
        "lib/forge-std/src/Vm.sol"
      ],
      "versionRequirement": ">=0.6.2, <0.9.0",
      "artifacts": {
        "StdCheats": {
          "0.8.21+commit.d9974bed.Darwin.appleclang": "StdCheats.sol/StdCheats.json"
        },
        "StdCheatsSafe": {
          "0.8.21+commit.d9974bed.Darwin.appleclang": "StdCheats.sol/StdCheatsSafe.json"
        }
      }
    },
    "lib/forge-std/src/StdError.sol": {
      "lastModificationDate": 1691430201971,
      "contentHash": "64c896e1276a291776e5ea5aecb3870a",
      "sourceName": "lib/forge-std/src/StdError.sol",
      "solcConfig": {
        "settings": {
          "optimizer": {
            "enabled": true,
            "runs": 200
          },
          "metadata": {
            "useLiteralContent": false,
            "bytecodeHash": "ipfs",
            "appendCBOR": true
          },
          "outputSelection": {
            "*": {
              "": [
                "ast"
              ],
              "*": [
                "abi",
                "evm.bytecode",
                "evm.deployedBytecode",
                "evm.methodIdentifiers",
                "metadata"
              ]
            }
          },
          "evmVersion": "paris",
          "libraries": {}
        }
      },
      "imports": [],
      "versionRequirement": ">=0.6.2, <0.9.0",
      "artifacts": {
        "stdError": {
          "0.8.21+commit.d9974bed.Darwin.appleclang": "StdError.sol/stdError.json"
        }
      }
    },
    "lib/forge-std/src/StdInvariant.sol": {
      "lastModificationDate": 1691430201972,
      "contentHash": "6d12d54c05754ad4e03066726dca3a84",
      "sourceName": "lib/forge-std/src/StdInvariant.sol",
      "solcConfig": {
        "settings": {
          "optimizer": {
            "enabled": true,
            "runs": 200
          },
          "metadata": {
            "useLiteralContent": false,
            "bytecodeHash": "ipfs",
            "appendCBOR": true
          },
          "outputSelection": {
            "*": {
              "": [
                "ast"
              ],
              "*": [
                "abi",
                "evm.bytecode",
                "evm.deployedBytecode",
                "evm.methodIdentifiers",
                "metadata"
              ]
            }
          },
          "evmVersion": "paris",
          "libraries": {}
        }
      },
      "imports": [],
      "versionRequirement": ">=0.6.2, <0.9.0",
      "artifacts": {
        "StdInvariant": {
          "0.8.21+commit.d9974bed.Darwin.appleclang": "StdInvariant.sol/StdInvariant.json"
        }
      }
    },
    "lib/forge-std/src/StdJson.sol": {
      "lastModificationDate": 1691430201972,
      "contentHash": "2e1d13674e152408867795362d833c24",
      "sourceName": "lib/forge-std/src/StdJson.sol",
      "solcConfig": {
        "settings": {
          "optimizer": {
            "enabled": true,
            "runs": 200
          },
          "metadata": {
            "useLiteralContent": false,
            "bytecodeHash": "ipfs",
            "appendCBOR": true
          },
          "outputSelection": {
            "*": {
              "": [
                "ast"
              ],
              "*": [
                "abi",
                "evm.bytecode",
                "evm.deployedBytecode",
                "evm.methodIdentifiers",
                "metadata"
              ]
            }
          },
          "evmVersion": "paris",
          "libraries": {}
        }
      },
      "imports": [
        "lib/forge-std/src/Vm.sol"
      ],
      "versionRequirement": ">=0.6.0, <0.9.0",
      "artifacts": {
        "stdJson": {
          "0.8.21+commit.d9974bed.Darwin.appleclang": "StdJson.sol/stdJson.json"
        }
      }
    },
    "lib/forge-std/src/StdMath.sol": {
      "lastModificationDate": 1691430201972,
      "contentHash": "9da8f453eba6bb98f3d75bc6822bfb29",
      "sourceName": "lib/forge-std/src/StdMath.sol",
      "solcConfig": {
        "settings": {
          "optimizer": {
            "enabled": true,
            "runs": 200
          },
          "metadata": {
            "useLiteralContent": false,
            "bytecodeHash": "ipfs",
            "appendCBOR": true
          },
          "outputSelection": {
            "*": {
              "": [
                "ast"
              ],
              "*": [
                "abi",
                "evm.bytecode",
                "evm.deployedBytecode",
                "evm.methodIdentifiers",
                "metadata"
              ]
            }
          },
          "evmVersion": "paris",
          "libraries": {}
        }
      },
      "imports": [],
      "versionRequirement": ">=0.6.2, <0.9.0",
      "artifacts": {
        "stdMath": {
          "0.8.21+commit.d9974bed.Darwin.appleclang": "StdMath.sol/stdMath.json"
        }
      }
    },
    "lib/forge-std/src/StdStorage.sol": {
      "lastModificationDate": 1691430201972,
      "contentHash": "4fc0ff0cb196a405e5a4c9fa1c6acccb",
      "sourceName": "lib/forge-std/src/StdStorage.sol",
      "solcConfig": {
        "settings": {
          "optimizer": {
            "enabled": true,
            "runs": 200
          },
          "metadata": {
            "useLiteralContent": false,
            "bytecodeHash": "ipfs",
            "appendCBOR": true
          },
          "outputSelection": {
            "*": {
              "": [
                "ast"
              ],
              "*": [
                "abi",
                "evm.bytecode",
                "evm.deployedBytecode",
                "evm.methodIdentifiers",
                "metadata"
              ]
            }
          },
          "evmVersion": "paris",
          "libraries": {}
        }
      },
      "imports": [
        "lib/forge-std/src/Vm.sol"
      ],
      "versionRequirement": ">=0.6.2, <0.9.0",
      "artifacts": {
        "stdStorage": {
          "0.8.21+commit.d9974bed.Darwin.appleclang": "StdStorage.sol/stdStorage.json"
        },
        "stdStorageSafe": {
          "0.8.21+commit.d9974bed.Darwin.appleclang": "StdStorage.sol/stdStorageSafe.json"
        }
      }
    },
    "lib/forge-std/src/StdStyle.sol": {
      "lastModificationDate": 1691430201972,
      "contentHash": "6281165a12aa639705c691fccefd855e",
      "sourceName": "lib/forge-std/src/StdStyle.sol",
      "solcConfig": {
        "settings": {
          "optimizer": {
            "enabled": true,
            "runs": 200
          },
          "metadata": {
            "useLiteralContent": false,
            "bytecodeHash": "ipfs",
            "appendCBOR": true
          },
          "outputSelection": {
            "*": {
              "": [
                "ast"
              ],
              "*": [
                "abi",
                "evm.bytecode",
                "evm.deployedBytecode",
                "evm.methodIdentifiers",
                "metadata"
              ]
            }
          },
          "evmVersion": "paris",
          "libraries": {}
        }
      },
      "imports": [
        "lib/forge-std/src/Vm.sol"
      ],
      "versionRequirement": ">=0.4.22, <0.9.0",
      "artifacts": {
        "StdStyle": {
          "0.8.21+commit.d9974bed.Darwin.appleclang": "StdStyle.sol/StdStyle.json"
        }
      }
    },
    "lib/forge-std/src/StdUtils.sol": {
      "lastModificationDate": 1691430201972,
      "contentHash": "3ce83748fd76644688f916c9cced545b",
      "sourceName": "lib/forge-std/src/StdUtils.sol",
      "solcConfig": {
        "settings": {
          "optimizer": {
            "enabled": true,
            "runs": 200
          },
          "metadata": {
            "useLiteralContent": false,
            "bytecodeHash": "ipfs",
            "appendCBOR": true
          },
          "outputSelection": {
            "*": {
              "": [
                "ast"
              ],
              "*": [
                "abi",
                "evm.bytecode",
                "evm.deployedBytecode",
                "evm.methodIdentifiers",
                "metadata"
              ]
            }
          },
          "evmVersion": "paris",
          "libraries": {}
        }
      },
      "imports": [
        "lib/forge-std/src/Vm.sol",
        "lib/forge-std/src/interfaces/IMulticall3.sol"
      ],
      "versionRequirement": ">=0.6.2, <0.9.0",
      "artifacts": {
        "StdUtils": {
          "0.8.21+commit.d9974bed.Darwin.appleclang": "StdUtils.sol/StdUtils.json"
        }
      }
    },
    "lib/forge-std/src/Test.sol": {
      "lastModificationDate": 1691430202839,
      "contentHash": "c67db2c47c2e757cc33d38d6db0b1562",
      "sourceName": "lib/forge-std/src/Test.sol",
      "solcConfig": {
        "settings": {
          "optimizer": {
            "enabled": true,
            "runs": 200
          },
          "metadata": {
            "useLiteralContent": false,
            "bytecodeHash": "ipfs",
            "appendCBOR": true
          },
          "outputSelection": {
            "*": {
              "": [
                "ast"
              ],
              "*": [
                "abi",
                "evm.bytecode",
                "evm.deployedBytecode",
                "evm.methodIdentifiers",
                "metadata"
              ]
            }
          },
          "evmVersion": "paris",
          "libraries": {}
        }
      },
      "imports": [
        "lib/forge-std/lib/ds-test/src/test.sol",
        "lib/forge-std/src/Base.sol",
        "lib/forge-std/src/StdAssertions.sol",
        "lib/forge-std/src/StdChains.sol",
        "lib/forge-std/src/StdCheats.sol",
        "lib/forge-std/src/StdError.sol",
        "lib/forge-std/src/StdInvariant.sol",
        "lib/forge-std/src/StdJson.sol",
        "lib/forge-std/src/StdMath.sol",
        "lib/forge-std/src/StdStorage.sol",
        "lib/forge-std/src/StdStyle.sol",
        "lib/forge-std/src/StdUtils.sol",
        "lib/forge-std/src/Vm.sol",
        "lib/forge-std/src/console.sol",
        "lib/forge-std/src/console2.sol",
        "lib/forge-std/src/interfaces/IMulticall3.sol",
        "lib/forge-std/src/safeconsole.sol"
      ],
      "versionRequirement": ">=0.6.2, <0.9.0",
      "artifacts": {
        "Test": {
          "0.8.21+commit.d9974bed.Darwin.appleclang": "Test.sol/Test.json"
        }
      }
    },
    "lib/forge-std/src/Vm.sol": {
      "lastModificationDate": 1691430201972,
      "contentHash": "b098c2721502365797aae8d0ee1babb8",
      "sourceName": "lib/forge-std/src/Vm.sol",
      "solcConfig": {
        "settings": {
          "optimizer": {
            "enabled": true,
            "runs": 200
          },
          "metadata": {
            "useLiteralContent": false,
            "bytecodeHash": "ipfs",
            "appendCBOR": true
          },
          "outputSelection": {
            "*": {
              "": [
                "ast"
              ],
              "*": [
                "abi",
                "evm.bytecode",
                "evm.deployedBytecode",
                "evm.methodIdentifiers",
                "metadata"
              ]
            }
          },
          "evmVersion": "paris",
          "libraries": {}
        }
      },
      "imports": [],
      "versionRequirement": ">=0.6.2, <0.9.0",
      "artifacts": {
        "Vm": {
          "0.8.21+commit.d9974bed.Darwin.appleclang": "Vm.sol/Vm.json"
        },
        "VmSafe": {
          "0.8.21+commit.d9974bed.Darwin.appleclang": "Vm.sol/VmSafe.json"
        }
      }
    },
    "lib/forge-std/src/console.sol": {
      "lastModificationDate": 1691430201973,
      "contentHash": "100b8a33b917da1147740d7ab8b0ded3",
      "sourceName": "lib/forge-std/src/console.sol",
      "solcConfig": {
        "settings": {
          "optimizer": {
            "enabled": true,
            "runs": 200
          },
          "metadata": {
            "useLiteralContent": false,
            "bytecodeHash": "ipfs",
            "appendCBOR": true
          },
          "outputSelection": {
            "*": {
              "": [
                "ast"
              ],
              "*": [
                "abi",
                "evm.bytecode",
                "evm.deployedBytecode",
                "evm.methodIdentifiers",
                "metadata"
              ]
            }
          },
          "evmVersion": "paris",
          "libraries": {}
        }
      },
      "imports": [],
      "versionRequirement": ">=0.4.22, <0.9.0",
      "artifacts": {
        "console": {
          "0.8.21+commit.d9974bed.Darwin.appleclang": "console.sol/console.json"
        }
      }
    },
    "lib/forge-std/src/console2.sol": {
      "lastModificationDate": 1691430201973,
      "contentHash": "491ca717c1915995e78cc361485a3067",
      "sourceName": "lib/forge-std/src/console2.sol",
      "solcConfig": {
        "settings": {
          "optimizer": {
            "enabled": true,
            "runs": 200
          },
          "metadata": {
            "useLiteralContent": false,
            "bytecodeHash": "ipfs",
            "appendCBOR": true
          },
          "outputSelection": {
            "*": {
              "": [
                "ast"
              ],
              "*": [
                "abi",
                "evm.bytecode",
                "evm.deployedBytecode",
                "evm.methodIdentifiers",
                "metadata"
              ]
            }
          },
          "evmVersion": "paris",
          "libraries": {}
        }
      },
      "imports": [],
      "versionRequirement": ">=0.4.22, <0.9.0",
      "artifacts": {
        "console2": {
          "0.8.21+commit.d9974bed.Darwin.appleclang": "console2.sol/console2.json"
        }
      }
    },
    "lib/forge-std/src/interfaces/IMulticall3.sol": {
      "lastModificationDate": 1691430201974,
      "contentHash": "7b131ca1ca32ef6378b7b9ad5488b901",
      "sourceName": "lib/forge-std/src/interfaces/IMulticall3.sol",
      "solcConfig": {
        "settings": {
          "optimizer": {
            "enabled": true,
            "runs": 200
          },
          "metadata": {
            "useLiteralContent": false,
            "bytecodeHash": "ipfs",
            "appendCBOR": true
          },
          "outputSelection": {
            "*": {
              "": [
                "ast"
              ],
              "*": [
                "abi",
                "evm.bytecode",
                "evm.deployedBytecode",
                "evm.methodIdentifiers",
                "metadata"
              ]
            }
          },
          "evmVersion": "paris",
          "libraries": {}
        }
      },
      "imports": [],
      "versionRequirement": ">=0.6.2, <0.9.0",
      "artifacts": {
        "IMulticall3": {
          "0.8.21+commit.d9974bed.Darwin.appleclang": "IMulticall3.sol/IMulticall3.json"
        }
      }
    },
    "lib/forge-std/src/safeconsole.sol": {
      "lastModificationDate": 1691430201974,
      "contentHash": "ac3b1bf5a444db5db3656021830258a8",
      "sourceName": "lib/forge-std/src/safeconsole.sol",
      "solcConfig": {
        "settings": {
          "optimizer": {
            "enabled": true,
            "runs": 200
          },
          "metadata": {
            "useLiteralContent": false,
            "bytecodeHash": "ipfs",
            "appendCBOR": true
          },
          "outputSelection": {
            "*": {
              "": [
                "ast"
              ],
              "*": [
                "abi",
                "evm.bytecode",
                "evm.deployedBytecode",
                "evm.methodIdentifiers",
                "metadata"
              ]
            }
          },
          "evmVersion": "paris",
          "libraries": {}
        }
      },
      "imports": [],
      "versionRequirement": ">=0.6.2, <0.9.0",
      "artifacts": {
        "safeconsole": {
          "0.8.21+commit.d9974bed.Darwin.appleclang": "safeconsole.sol/safeconsole.json"
        }
      }
    },
    "lib/openzeppelin-contracts/contracts/access/Ownable.sol": {
      "lastModificationDate": 1691431072734,
      "contentHash": "5a20b2cad87ddb61c7a3a6af21289e28",
      "sourceName": "lib/openzeppelin-contracts/contracts/access/Ownable.sol",
      "solcConfig": {
        "settings": {
          "optimizer": {
            "enabled": true,
            "runs": 200
          },
          "metadata": {
            "useLiteralContent": false,
            "bytecodeHash": "ipfs",
            "appendCBOR": true
          },
          "outputSelection": {
            "*": {
              "": [
                "ast"
              ],
              "*": [
                "abi",
                "evm.bytecode",
                "evm.deployedBytecode",
                "evm.methodIdentifiers",
                "metadata"
              ]
            }
          },
          "evmVersion": "paris",
          "libraries": {}
        }
      },
      "imports": [
        "lib/openzeppelin-contracts/contracts/utils/Context.sol"
      ],
      "versionRequirement": "^0.8.0",
      "artifacts": {
        "Ownable": {
          "0.8.21+commit.d9974bed.Darwin.appleclang": "Ownable.sol/Ownable.json"
        }
      }
    },
    "lib/openzeppelin-contracts/contracts/interfaces/IERC1967.sol": {
      "lastModificationDate": 1691431072741,
      "contentHash": "d0d060231a45da7a1eecbb5cd286fa40",
      "sourceName": "lib/openzeppelin-contracts/contracts/interfaces/IERC1967.sol",
      "solcConfig": {
        "settings": {
          "optimizer": {
            "enabled": true,
            "runs": 200
          },
          "metadata": {
            "useLiteralContent": false,
            "bytecodeHash": "ipfs",
            "appendCBOR": true
          },
          "outputSelection": {
            "*": {
              "": [
                "ast"
              ],
              "*": [
                "abi",
                "evm.bytecode",
                "evm.deployedBytecode",
                "evm.methodIdentifiers",
                "metadata"
              ]
            }
          },
          "evmVersion": "paris",
          "libraries": {}
        }
      },
      "imports": [],
      "versionRequirement": "^0.8.0",
      "artifacts": {
        "IERC1967": {
          "0.8.21+commit.d9974bed.Darwin.appleclang": "IERC1967.sol/IERC1967.json"
        }
      }
    },
    "lib/openzeppelin-contracts/contracts/interfaces/draft-IERC1822.sol": {
      "lastModificationDate": 1691431072745,
      "contentHash": "2858d98e74e67987ec81b39605230b74",
      "sourceName": "lib/openzeppelin-contracts/contracts/interfaces/draft-IERC1822.sol",
      "solcConfig": {
        "settings": {
          "optimizer": {
            "enabled": true,
            "runs": 200
          },
          "metadata": {
            "useLiteralContent": false,
            "bytecodeHash": "ipfs",
            "appendCBOR": true
          },
          "outputSelection": {
            "*": {
              "": [
                "ast"
              ],
              "*": [
                "abi",
                "evm.bytecode",
                "evm.deployedBytecode",
                "evm.methodIdentifiers",
                "metadata"
              ]
            }
          },
          "evmVersion": "paris",
          "libraries": {}
        }
      },
      "imports": [],
      "versionRequirement": "^0.8.0",
      "artifacts": {
        "IERC1822Proxiable": {
          "0.8.21+commit.d9974bed.Darwin.appleclang": "draft-IERC1822.sol/IERC1822Proxiable.json"
        }
      }
    },
    "lib/openzeppelin-contracts/contracts/proxy/ERC1967/ERC1967Proxy.sol": {
      "lastModificationDate": 1691431072757,
      "contentHash": "3fc3c7c0a2956f36e766691bb9473b06",
      "sourceName": "lib/openzeppelin-contracts/contracts/proxy/ERC1967/ERC1967Proxy.sol",
      "solcConfig": {
        "settings": {
          "optimizer": {
            "enabled": true,
            "runs": 200
          },
          "metadata": {
            "useLiteralContent": false,
            "bytecodeHash": "ipfs",
            "appendCBOR": true
          },
          "outputSelection": {
            "*": {
              "": [
                "ast"
              ],
              "*": [
                "abi",
                "evm.bytecode",
                "evm.deployedBytecode",
                "evm.methodIdentifiers",
                "metadata"
              ]
            }
          },
          "evmVersion": "paris",
          "libraries": {}
        }
      },
      "imports": [
        "lib/openzeppelin-contracts/contracts/interfaces/IERC1967.sol",
        "lib/openzeppelin-contracts/contracts/interfaces/draft-IERC1822.sol",
        "lib/openzeppelin-contracts/contracts/proxy/ERC1967/ERC1967Upgrade.sol",
        "lib/openzeppelin-contracts/contracts/proxy/Proxy.sol",
        "lib/openzeppelin-contracts/contracts/proxy/beacon/IBeacon.sol",
        "lib/openzeppelin-contracts/contracts/utils/Address.sol",
        "lib/openzeppelin-contracts/contracts/utils/StorageSlot.sol"
      ],
      "versionRequirement": "^0.8.0",
      "artifacts": {
        "ERC1967Proxy": {
          "0.8.21+commit.d9974bed.Darwin.appleclang": "ERC1967Proxy.sol/ERC1967Proxy.json"
        }
      }
    },
    "lib/openzeppelin-contracts/contracts/proxy/ERC1967/ERC1967Upgrade.sol": {
      "lastModificationDate": 1691431072757,
      "contentHash": "a127706394bead18392601a20d44867a",
      "sourceName": "lib/openzeppelin-contracts/contracts/proxy/ERC1967/ERC1967Upgrade.sol",
      "solcConfig": {
        "settings": {
          "optimizer": {
            "enabled": true,
            "runs": 200
          },
          "metadata": {
            "useLiteralContent": false,
            "bytecodeHash": "ipfs",
            "appendCBOR": true
          },
          "outputSelection": {
            "*": {
              "": [
                "ast"
              ],
              "*": [
                "abi",
                "evm.bytecode",
                "evm.deployedBytecode",
                "evm.methodIdentifiers",
                "metadata"
              ]
            }
          },
          "evmVersion": "paris",
          "libraries": {}
        }
      },
      "imports": [
        "lib/openzeppelin-contracts/contracts/interfaces/IERC1967.sol",
        "lib/openzeppelin-contracts/contracts/interfaces/draft-IERC1822.sol",
        "lib/openzeppelin-contracts/contracts/proxy/beacon/IBeacon.sol",
        "lib/openzeppelin-contracts/contracts/utils/Address.sol",
        "lib/openzeppelin-contracts/contracts/utils/StorageSlot.sol"
      ],
      "versionRequirement": "^0.8.2",
      "artifacts": {
        "ERC1967Upgrade": {
          "0.8.21+commit.d9974bed.Darwin.appleclang": "ERC1967Upgrade.sol/ERC1967Upgrade.json"
        }
      }
    },
    "lib/openzeppelin-contracts/contracts/proxy/Proxy.sol": {
      "lastModificationDate": 1691431072757,
      "contentHash": "40b3d81a836d50ff47e03893dcaaf204",
      "sourceName": "lib/openzeppelin-contracts/contracts/proxy/Proxy.sol",
      "solcConfig": {
        "settings": {
          "optimizer": {
            "enabled": true,
            "runs": 200
          },
          "metadata": {
            "useLiteralContent": false,
            "bytecodeHash": "ipfs",
            "appendCBOR": true
          },
          "outputSelection": {
            "*": {
              "": [
                "ast"
              ],
              "*": [
                "abi",
                "evm.bytecode",
                "evm.deployedBytecode",
                "evm.methodIdentifiers",
                "metadata"
              ]
            }
          },
          "evmVersion": "paris",
          "libraries": {}
        }
      },
      "imports": [],
      "versionRequirement": "^0.8.0",
      "artifacts": {
        "Proxy": {
          "0.8.21+commit.d9974bed.Darwin.appleclang": "Proxy.sol/Proxy.json"
        }
      }
    },
    "lib/openzeppelin-contracts/contracts/proxy/beacon/IBeacon.sol": {
      "lastModificationDate": 1691431072758,
      "contentHash": "b6bd23bf19e90b771337037706470933",
      "sourceName": "lib/openzeppelin-contracts/contracts/proxy/beacon/IBeacon.sol",
      "solcConfig": {
        "settings": {
          "optimizer": {
            "enabled": true,
            "runs": 200
          },
          "metadata": {
            "useLiteralContent": false,
            "bytecodeHash": "ipfs",
            "appendCBOR": true
          },
          "outputSelection": {
            "*": {
              "": [
                "ast"
              ],
              "*": [
                "abi",
                "evm.bytecode",
                "evm.deployedBytecode",
                "evm.methodIdentifiers",
                "metadata"
              ]
            }
          },
          "evmVersion": "paris",
          "libraries": {}
        }
      },
      "imports": [],
      "versionRequirement": "^0.8.0",
      "artifacts": {
        "IBeacon": {
          "0.8.21+commit.d9974bed.Darwin.appleclang": "IBeacon.sol/IBeacon.json"
        }
      }
    },
    "lib/openzeppelin-contracts/contracts/proxy/transparent/TransparentUpgradeableProxy.sol": {
      "lastModificationDate": 1691431072758,
      "contentHash": "1286aa8d056c7120d1a2da252e310d2f",
      "sourceName": "lib/openzeppelin-contracts/contracts/proxy/transparent/TransparentUpgradeableProxy.sol",
      "solcConfig": {
        "settings": {
          "optimizer": {
            "enabled": true,
            "runs": 200
          },
          "metadata": {
            "useLiteralContent": false,
            "bytecodeHash": "ipfs",
            "appendCBOR": true
          },
          "outputSelection": {
            "*": {
              "": [
                "ast"
              ],
              "*": [
                "abi",
                "evm.bytecode",
                "evm.deployedBytecode",
                "evm.methodIdentifiers",
                "metadata"
              ]
            }
          },
          "evmVersion": "paris",
          "libraries": {}
        }
      },
      "imports": [
        "lib/openzeppelin-contracts/contracts/interfaces/IERC1967.sol",
        "lib/openzeppelin-contracts/contracts/interfaces/draft-IERC1822.sol",
        "lib/openzeppelin-contracts/contracts/proxy/ERC1967/ERC1967Proxy.sol",
        "lib/openzeppelin-contracts/contracts/proxy/ERC1967/ERC1967Upgrade.sol",
        "lib/openzeppelin-contracts/contracts/proxy/Proxy.sol",
        "lib/openzeppelin-contracts/contracts/proxy/beacon/IBeacon.sol",
        "lib/openzeppelin-contracts/contracts/utils/Address.sol",
        "lib/openzeppelin-contracts/contracts/utils/StorageSlot.sol"
      ],
      "versionRequirement": "^0.8.0",
      "artifacts": {
        "ITransparentUpgradeableProxy": {
          "0.8.21+commit.d9974bed.Darwin.appleclang": "TransparentUpgradeableProxy.sol/ITransparentUpgradeableProxy.json"
        },
        "TransparentUpgradeableProxy": {
          "0.8.21+commit.d9974bed.Darwin.appleclang": "TransparentUpgradeableProxy.sol/TransparentUpgradeableProxy.json"
        }
      }
    },
    "lib/openzeppelin-contracts/contracts/proxy/utils/Initializable.sol": {
      "lastModificationDate": 1691431072758,
      "contentHash": "5efeb93e6b1c83c754da2846c2da51a7",
      "sourceName": "lib/openzeppelin-contracts/contracts/proxy/utils/Initializable.sol",
      "solcConfig": {
        "settings": {
          "optimizer": {
            "enabled": true,
            "runs": 200
          },
          "metadata": {
            "useLiteralContent": false,
            "bytecodeHash": "ipfs",
            "appendCBOR": true
          },
          "outputSelection": {
            "*": {
              "": [
                "ast"
              ],
              "*": [
                "abi",
                "evm.bytecode",
                "evm.deployedBytecode",
                "evm.methodIdentifiers",
                "metadata"
              ]
            }
          },
          "evmVersion": "paris",
          "libraries": {}
        }
      },
      "imports": [
        "lib/openzeppelin-contracts/contracts/utils/Address.sol"
      ],
      "versionRequirement": "^0.8.2",
      "artifacts": {
        "Initializable": {
          "0.8.21+commit.d9974bed.Darwin.appleclang": "Initializable.sol/Initializable.json"
        }
      }
    },
    "lib/openzeppelin-contracts/contracts/security/Pausable.sol": {
      "lastModificationDate": 1691431072759,
      "contentHash": "25c8108f36fdd472bc78d4c4af240c11",
      "sourceName": "lib/openzeppelin-contracts/contracts/security/Pausable.sol",
      "solcConfig": {
        "settings": {
          "optimizer": {
            "enabled": true,
            "runs": 200
          },
          "metadata": {
            "useLiteralContent": false,
            "bytecodeHash": "ipfs",
            "appendCBOR": true
          },
          "outputSelection": {
            "*": {
              "": [
                "ast"
              ],
              "*": [
                "abi",
                "evm.bytecode",
                "evm.deployedBytecode",
                "evm.methodIdentifiers",
                "metadata"
              ]
            }
          },
          "evmVersion": "paris",
          "libraries": {}
        }
      },
      "imports": [
        "lib/openzeppelin-contracts/contracts/utils/Context.sol"
      ],
      "versionRequirement": "^0.8.0",
      "artifacts": {
        "Pausable": {
          "0.8.21+commit.d9974bed.Darwin.appleclang": "Pausable.sol/Pausable.json"
        }
      }
    },
    "lib/openzeppelin-contracts/contracts/token/ERC20/ERC20.sol": {
      "lastModificationDate": 1691431072762,
      "contentHash": "3ae5166c6827a9cf1a7a462d1632b464",
      "sourceName": "lib/openzeppelin-contracts/contracts/token/ERC20/ERC20.sol",
      "solcConfig": {
        "settings": {
          "optimizer": {
            "enabled": true,
            "runs": 200
          },
          "metadata": {
            "useLiteralContent": false,
            "bytecodeHash": "ipfs",
            "appendCBOR": true
          },
          "outputSelection": {
            "*": {
              "": [
                "ast"
              ],
              "*": [
                "abi",
                "evm.bytecode",
                "evm.deployedBytecode",
                "evm.methodIdentifiers",
                "metadata"
              ]
            }
          },
          "evmVersion": "paris",
          "libraries": {}
        }
      },
      "imports": [
        "lib/openzeppelin-contracts/contracts/token/ERC20/IERC20.sol",
        "lib/openzeppelin-contracts/contracts/token/ERC20/extensions/IERC20Metadata.sol",
        "lib/openzeppelin-contracts/contracts/utils/Context.sol"
      ],
      "versionRequirement": "^0.8.0",
      "artifacts": {
        "ERC20": {
          "0.8.21+commit.d9974bed.Darwin.appleclang": "ERC20.sol/ERC20.json"
        }
      }
    },
    "lib/openzeppelin-contracts/contracts/token/ERC20/IERC20.sol": {
      "lastModificationDate": 1691431072762,
      "contentHash": "df36f7051335cd1e748b1b6463b7fdd3",
      "sourceName": "lib/openzeppelin-contracts/contracts/token/ERC20/IERC20.sol",
      "solcConfig": {
        "settings": {
          "optimizer": {
            "enabled": true,
            "runs": 200
          },
          "metadata": {
            "useLiteralContent": false,
            "bytecodeHash": "ipfs",
            "appendCBOR": true
          },
          "outputSelection": {
            "*": {
              "": [
                "ast"
              ],
              "*": [
                "abi",
                "evm.bytecode",
                "evm.deployedBytecode",
                "evm.methodIdentifiers",
                "metadata"
              ]
            }
          },
          "evmVersion": "paris",
          "libraries": {}
        }
      },
      "imports": [],
      "versionRequirement": "^0.8.0",
      "artifacts": {
        "IERC20": {
          "0.8.21+commit.d9974bed.Darwin.appleclang": "IERC20.sol/IERC20.json"
        }
      }
    },
    "lib/openzeppelin-contracts/contracts/token/ERC20/extensions/IERC20Metadata.sol": {
      "lastModificationDate": 1691431072764,
      "contentHash": "909ab67fc5c25033fe6cd364f8c056f9",
      "sourceName": "lib/openzeppelin-contracts/contracts/token/ERC20/extensions/IERC20Metadata.sol",
      "solcConfig": {
        "settings": {
          "optimizer": {
            "enabled": true,
            "runs": 200
          },
          "metadata": {
            "useLiteralContent": false,
            "bytecodeHash": "ipfs",
            "appendCBOR": true
          },
          "outputSelection": {
            "*": {
              "": [
                "ast"
              ],
              "*": [
                "abi",
                "evm.bytecode",
                "evm.deployedBytecode",
                "evm.methodIdentifiers",
                "metadata"
              ]
            }
          },
          "evmVersion": "paris",
          "libraries": {}
        }
      },
      "imports": [
        "lib/openzeppelin-contracts/contracts/token/ERC20/IERC20.sol"
      ],
      "versionRequirement": "^0.8.0",
      "artifacts": {
        "IERC20Metadata": {
          "0.8.21+commit.d9974bed.Darwin.appleclang": "IERC20Metadata.sol/IERC20Metadata.json"
        }
      }
    },
    "lib/openzeppelin-contracts/contracts/utils/Address.sol": {
      "lastModificationDate": 1691431072769,
      "contentHash": "211ffd288c1588ba8c10eae668ca3c66",
      "sourceName": "lib/openzeppelin-contracts/contracts/utils/Address.sol",
      "solcConfig": {
        "settings": {
          "optimizer": {
            "enabled": true,
            "runs": 200
          },
          "metadata": {
            "useLiteralContent": false,
            "bytecodeHash": "ipfs",
            "appendCBOR": true
          },
          "outputSelection": {
            "*": {
              "": [
                "ast"
              ],
              "*": [
                "abi",
                "evm.bytecode",
                "evm.deployedBytecode",
                "evm.methodIdentifiers",
                "metadata"
              ]
            }
          },
          "evmVersion": "paris",
          "libraries": {}
        }
      },
      "imports": [],
      "versionRequirement": "^0.8.1",
      "artifacts": {
        "Address": {
          "0.8.21+commit.d9974bed.Darwin.appleclang": "Address.sol/Address.json"
        }
      }
    },
    "lib/openzeppelin-contracts/contracts/utils/Context.sol": {
      "lastModificationDate": 1691431072770,
      "contentHash": "5f2c5c4b6af2dd4551027144797bc8be",
      "sourceName": "lib/openzeppelin-contracts/contracts/utils/Context.sol",
      "solcConfig": {
        "settings": {
          "optimizer": {
            "enabled": true,
            "runs": 200
          },
          "metadata": {
            "useLiteralContent": false,
            "bytecodeHash": "ipfs",
            "appendCBOR": true
          },
          "outputSelection": {
            "*": {
              "": [
                "ast"
              ],
              "*": [
                "abi",
                "evm.bytecode",
                "evm.deployedBytecode",
                "evm.methodIdentifiers",
                "metadata"
              ]
            }
          },
          "evmVersion": "paris",
          "libraries": {}
        }
      },
      "imports": [],
      "versionRequirement": "^0.8.0",
      "artifacts": {
        "Context": {
          "0.8.21+commit.d9974bed.Darwin.appleclang": "Context.sol/Context.json"
        }
      }
    },
    "lib/openzeppelin-contracts/contracts/utils/StorageSlot.sol": {
      "lastModificationDate": 1691431072770,
      "contentHash": "682f7dd1f2e1147c8390e7575deceb2d",
      "sourceName": "lib/openzeppelin-contracts/contracts/utils/StorageSlot.sol",
      "solcConfig": {
        "settings": {
          "optimizer": {
            "enabled": true,
            "runs": 200
          },
          "metadata": {
            "useLiteralContent": false,
            "bytecodeHash": "ipfs",
            "appendCBOR": true
          },
          "outputSelection": {
            "*": {
              "": [
                "ast"
              ],
              "*": [
                "abi",
                "evm.bytecode",
                "evm.deployedBytecode",
                "evm.methodIdentifiers",
                "metadata"
              ]
            }
          },
          "evmVersion": "paris",
          "libraries": {}
        }
      },
      "imports": [],
      "versionRequirement": "^0.8.0",
      "artifacts": {
        "StorageSlot": {
          "0.8.21+commit.d9974bed.Darwin.appleclang": "StorageSlot.sol/StorageSlot.json"
        }
      }
    },
    "script/Counter.s.sol": {
      "lastModificationDate": 1691430200546,
      "contentHash": "7539680fbd3ad49c6632713cc2bb6bf6",
      "sourceName": "script/Counter.s.sol",
      "solcConfig": {
        "settings": {
          "optimizer": {
            "enabled": true,
            "runs": 200
          },
          "metadata": {
            "useLiteralContent": false,
            "bytecodeHash": "ipfs",
            "appendCBOR": true
          },
          "outputSelection": {
            "*": {
              "": [
                "ast"
              ],
              "*": [
                "abi",
                "evm.bytecode",
                "evm.deployedBytecode",
                "evm.methodIdentifiers",
                "metadata"
              ]
            }
          },
          "evmVersion": "paris",
          "libraries": {}
        }
      },
      "imports": [
        "lib/forge-std/src/Base.sol",
        "lib/forge-std/src/Script.sol",
        "lib/forge-std/src/StdChains.sol",
        "lib/forge-std/src/StdCheats.sol",
        "lib/forge-std/src/StdJson.sol",
        "lib/forge-std/src/StdMath.sol",
        "lib/forge-std/src/StdStorage.sol",
        "lib/forge-std/src/StdStyle.sol",
        "lib/forge-std/src/StdUtils.sol",
        "lib/forge-std/src/Vm.sol",
        "lib/forge-std/src/console.sol",
        "lib/forge-std/src/console2.sol",
        "lib/forge-std/src/interfaces/IMulticall3.sol",
        "lib/forge-std/src/safeconsole.sol"
      ],
      "versionRequirement": "^0.8.13",
      "artifacts": {
        "CounterScript": {
          "0.8.21+commit.d9974bed.Darwin.appleclang": "Counter.s.sol/CounterScript.json"
        }
      }
    },
    "src/Proxy.sol": {
      "lastModificationDate": 1691440979756,
      "contentHash": "73b54fcf78681dc683112771b0af88b7",
      "sourceName": "src/Proxy.sol",
      "solcConfig": {
        "settings": {
          "optimizer": {
            "enabled": true,
            "runs": 200
          },
          "metadata": {
            "useLiteralContent": false,
            "bytecodeHash": "ipfs",
            "appendCBOR": true
          },
          "outputSelection": {
            "*": {
              "": [
                "ast"
              ],
              "*": [
                "abi",
                "evm.bytecode",
                "evm.deployedBytecode",
                "evm.methodIdentifiers",
                "metadata"
              ]
            }
          },
          "evmVersion": "paris",
          "libraries": {}
        }
      },
      "imports": [
        "lib/openzeppelin-contracts/contracts/access/Ownable.sol",
        "lib/openzeppelin-contracts/contracts/interfaces/IERC1967.sol",
        "lib/openzeppelin-contracts/contracts/interfaces/draft-IERC1822.sol",
        "lib/openzeppelin-contracts/contracts/proxy/ERC1967/ERC1967Proxy.sol",
        "lib/openzeppelin-contracts/contracts/proxy/ERC1967/ERC1967Upgrade.sol",
        "lib/openzeppelin-contracts/contracts/proxy/Proxy.sol",
        "lib/openzeppelin-contracts/contracts/proxy/beacon/IBeacon.sol",
        "lib/openzeppelin-contracts/contracts/proxy/transparent/TransparentUpgradeableProxy.sol",
        "lib/openzeppelin-contracts/contracts/proxy/utils/Initializable.sol",
        "lib/openzeppelin-contracts/contracts/utils/Address.sol",
        "lib/openzeppelin-contracts/contracts/utils/Context.sol",
        "lib/openzeppelin-contracts/contracts/utils/StorageSlot.sol"
      ],
      "versionRequirement": "^0.8.21",
      "artifacts": {
        "ProxyBridge": {
          "0.8.21+commit.d9974bed.Darwin.appleclang": "Proxy.sol/ProxyBridge.json"
        }
      }
    },
    "src/Staking.sol": {
      "lastModificationDate": 1691602909467,
      "contentHash": "b08573efc0ed1a126b82d60c3facdafa",
      "sourceName": "src/Staking.sol",
      "solcConfig": {
        "settings": {
          "optimizer": {
            "enabled": true,
            "runs": 200
          },
          "metadata": {
            "useLiteralContent": false,
            "bytecodeHash": "ipfs",
            "appendCBOR": true
          },
          "outputSelection": {
            "*": {
              "": [
                "ast"
              ],
              "*": [
                "abi",
                "evm.bytecode",
                "evm.deployedBytecode",
                "evm.methodIdentifiers",
                "metadata"
              ]
            }
          },
          "evmVersion": "paris",
          "libraries": {}
        }
      },
      "imports": [
        "lib/forge-std/lib/ds-test/src/test.sol",
        "lib/forge-std/src/Base.sol",
        "lib/forge-std/src/StdAssertions.sol",
        "lib/forge-std/src/StdChains.sol",
        "lib/forge-std/src/StdCheats.sol",
        "lib/forge-std/src/StdError.sol",
        "lib/forge-std/src/StdInvariant.sol",
        "lib/forge-std/src/StdJson.sol",
        "lib/forge-std/src/StdMath.sol",
        "lib/forge-std/src/StdStorage.sol",
        "lib/forge-std/src/StdStyle.sol",
        "lib/forge-std/src/StdUtils.sol",
        "lib/forge-std/src/Test.sol",
        "lib/forge-std/src/Vm.sol",
        "lib/forge-std/src/console.sol",
        "lib/forge-std/src/console2.sol",
        "lib/forge-std/src/interfaces/IMulticall3.sol",
        "lib/forge-std/src/safeconsole.sol",
        "lib/openzeppelin-contracts/contracts/access/Ownable.sol",
        "lib/openzeppelin-contracts/contracts/interfaces/IERC1967.sol",
        "lib/openzeppelin-contracts/contracts/interfaces/draft-IERC1822.sol",
        "lib/openzeppelin-contracts/contracts/proxy/ERC1967/ERC1967Proxy.sol",
        "lib/openzeppelin-contracts/contracts/proxy/ERC1967/ERC1967Upgrade.sol",
        "lib/openzeppelin-contracts/contracts/proxy/Proxy.sol",
        "lib/openzeppelin-contracts/contracts/proxy/beacon/IBeacon.sol",
        "lib/openzeppelin-contracts/contracts/proxy/utils/Initializable.sol",
        "lib/openzeppelin-contracts/contracts/security/Pausable.sol",
        "lib/openzeppelin-contracts/contracts/token/ERC20/ERC20.sol",
        "lib/openzeppelin-contracts/contracts/token/ERC20/IERC20.sol",
        "lib/openzeppelin-contracts/contracts/token/ERC20/extensions/IERC20Metadata.sol",
        "lib/openzeppelin-contracts/contracts/utils/Address.sol",
        "lib/openzeppelin-contracts/contracts/utils/Context.sol",
        "lib/openzeppelin-contracts/contracts/utils/StorageSlot.sol",
        "src/Token.sol"
      ],
      "versionRequirement": "^0.8.0",
      "artifacts": {
        "Staking": {
          "0.8.21+commit.d9974bed.Darwin.appleclang": "Staking.sol/Staking.json"
        }
      }
    },
    "src/Token.sol": {
      "lastModificationDate": 1691434416458,
      "contentHash": "fb70cdfa43c4d8fac770f391786466d5",
      "sourceName": "src/Token.sol",
      "solcConfig": {
        "settings": {
          "optimizer": {
            "enabled": true,
            "runs": 200
          },
          "metadata": {
            "useLiteralContent": false,
            "bytecodeHash": "ipfs",
            "appendCBOR": true
          },
          "outputSelection": {
            "*": {
              "": [
                "ast"
              ],
              "*": [
                "abi",
                "evm.bytecode",
                "evm.deployedBytecode",
                "evm.methodIdentifiers",
                "metadata"
              ]
            }
          },
          "evmVersion": "paris",
          "libraries": {}
        }
      },
      "imports": [
        "lib/openzeppelin-contracts/contracts/access/Ownable.sol",
        "lib/openzeppelin-contracts/contracts/security/Pausable.sol",
        "lib/openzeppelin-contracts/contracts/token/ERC20/ERC20.sol",
        "lib/openzeppelin-contracts/contracts/token/ERC20/IERC20.sol",
        "lib/openzeppelin-contracts/contracts/token/ERC20/extensions/IERC20Metadata.sol",
        "lib/openzeppelin-contracts/contracts/utils/Context.sol"
      ],
      "versionRequirement": "^0.8.0",
      "artifacts": {
        "Token": {
          "0.8.21+commit.d9974bed.Darwin.appleclang": "Token.sol/Token.json"
        }
      }
    },
    "test/Staking.t.sol": {
      "lastModificationDate": 1691602929495,
      "contentHash": "fe04a31e571d8e32906ae0a2ef8810a3",
      "sourceName": "test/Staking.t.sol",
      "solcConfig": {
        "settings": {
          "optimizer": {
            "enabled": true,
            "runs": 200
          },
          "metadata": {
            "useLiteralContent": false,
            "bytecodeHash": "ipfs",
            "appendCBOR": true
          },
          "outputSelection": {
            "*": {
              "": [
                "ast"
              ],
              "*": [
                "abi",
                "evm.bytecode",
                "evm.deployedBytecode",
                "evm.methodIdentifiers",
                "metadata"
              ]
            }
          },
          "evmVersion": "paris",
          "libraries": {}
        }
      },
      "imports": [
        "lib/forge-std/lib/ds-test/src/test.sol",
        "lib/forge-std/src/Base.sol",
        "lib/forge-std/src/StdAssertions.sol",
        "lib/forge-std/src/StdChains.sol",
        "lib/forge-std/src/StdCheats.sol",
        "lib/forge-std/src/StdError.sol",
        "lib/forge-std/src/StdInvariant.sol",
        "lib/forge-std/src/StdJson.sol",
        "lib/forge-std/src/StdMath.sol",
        "lib/forge-std/src/StdStorage.sol",
        "lib/forge-std/src/StdStyle.sol",
        "lib/forge-std/src/StdUtils.sol",
        "lib/forge-std/src/Test.sol",
        "lib/forge-std/src/Vm.sol",
        "lib/forge-std/src/console.sol",
        "lib/forge-std/src/console2.sol",
        "lib/forge-std/src/interfaces/IMulticall3.sol",
        "lib/forge-std/src/safeconsole.sol",
        "lib/openzeppelin-contracts/contracts/access/Ownable.sol",
        "lib/openzeppelin-contracts/contracts/interfaces/IERC1967.sol",
        "lib/openzeppelin-contracts/contracts/interfaces/draft-IERC1822.sol",
        "lib/openzeppelin-contracts/contracts/proxy/ERC1967/ERC1967Proxy.sol",
        "lib/openzeppelin-contracts/contracts/proxy/ERC1967/ERC1967Upgrade.sol",
        "lib/openzeppelin-contracts/contracts/proxy/Proxy.sol",
        "lib/openzeppelin-contracts/contracts/proxy/beacon/IBeacon.sol",
        "lib/openzeppelin-contracts/contracts/proxy/utils/Initializable.sol",
        "lib/openzeppelin-contracts/contracts/security/Pausable.sol",
        "lib/openzeppelin-contracts/contracts/token/ERC20/ERC20.sol",
        "lib/openzeppelin-contracts/contracts/token/ERC20/IERC20.sol",
        "lib/openzeppelin-contracts/contracts/token/ERC20/extensions/IERC20Metadata.sol",
        "lib/openzeppelin-contracts/contracts/utils/Address.sol",
        "lib/openzeppelin-contracts/contracts/utils/Context.sol",
        "lib/openzeppelin-contracts/contracts/utils/StorageSlot.sol",
        "src/Staking.sol",
        "src/Token.sol"
      ],
      "versionRequirement": "^0.8.13",
      "artifacts": {
        "TokenTest": {
          "0.8.21+commit.d9974bed.Darwin.appleclang": "Staking.t.sol/TokenTest.json"
        }
      }
    },
    "test/Token.t.sol": {
      "lastModificationDate": 1691434376968,
      "contentHash": "0271f7622a697484daeaa6b068cef9bb",
      "sourceName": "test/Token.t.sol",
      "solcConfig": {
        "settings": {
          "optimizer": {
            "enabled": true,
            "runs": 200
          },
          "metadata": {
            "useLiteralContent": false,
            "bytecodeHash": "ipfs",
            "appendCBOR": true
          },
          "outputSelection": {
            "*": {
              "": [
                "ast"
              ],
              "*": [
                "abi",
                "evm.bytecode",
                "evm.deployedBytecode",
                "evm.methodIdentifiers",
                "metadata"
              ]
            }
          },
          "evmVersion": "paris",
          "libraries": {}
        }
      },
      "imports": [
        "lib/forge-std/lib/ds-test/src/test.sol",
        "lib/forge-std/src/Base.sol",
        "lib/forge-std/src/StdAssertions.sol",
        "lib/forge-std/src/StdChains.sol",
        "lib/forge-std/src/StdCheats.sol",
        "lib/forge-std/src/StdError.sol",
        "lib/forge-std/src/StdInvariant.sol",
        "lib/forge-std/src/StdJson.sol",
        "lib/forge-std/src/StdMath.sol",
        "lib/forge-std/src/StdStorage.sol",
        "lib/forge-std/src/StdStyle.sol",
        "lib/forge-std/src/StdUtils.sol",
        "lib/forge-std/src/Test.sol",
        "lib/forge-std/src/Vm.sol",
        "lib/forge-std/src/console.sol",
        "lib/forge-std/src/console2.sol",
        "lib/forge-std/src/interfaces/IMulticall3.sol",
        "lib/forge-std/src/safeconsole.sol",
        "lib/openzeppelin-contracts/contracts/access/Ownable.sol",
        "lib/openzeppelin-contracts/contracts/security/Pausable.sol",
        "lib/openzeppelin-contracts/contracts/token/ERC20/ERC20.sol",
        "lib/openzeppelin-contracts/contracts/token/ERC20/IERC20.sol",
        "lib/openzeppelin-contracts/contracts/token/ERC20/extensions/IERC20Metadata.sol",
        "lib/openzeppelin-contracts/contracts/utils/Context.sol",
        "src/Token.sol"
      ],
      "versionRequirement": "^0.8.13",
      "artifacts": {
        "TokenTest": {
          "0.8.21+commit.d9974bed.Darwin.appleclang": "Token.t.sol/TokenTest.json"
        }
      }
    }
  }
}